fastnsq/__init__.py
fastnsq/app.py
fastnsq/bins/__init__.py
fastnsq/bins/nsq_stat
fastnsq/bins/nsq_tail
fastnsq/bins/nsq_to_file
fastnsq/bins/nsq_to_http
fastnsq/bins/nsq_to_nsq
fastnsq/bins/nsqadmin
fastnsq/bins/nsqd
fastnsq/bins/nsqlookupd
fastnsq/bins/to_nsq
fastnsq-0.0.5.dist-info/METADATA
fastnsq-0.0.5.dist-info/WHEEL
fastnsq-0.0.5.dist-info/entry_points.txt
fastnsq-0.0.5.dist-info/top_level.txt
fastnsq-0.0.5.dist-info/RECORD
